odoo/addons/product_packaging_type/README.rst
odoo/addons/product_packaging_type/__init__.py
odoo/addons/product_packaging_type/__manifest__.py
odoo/addons/product_packaging_type/data/product_packaging_type.xml
odoo/addons/product_packaging_type/i18n/ca.po
odoo/addons/product_packaging_type/i18n/es.po
odoo/addons/product_packaging_type/i18n/it.po
odoo/addons/product_packaging_type/i18n/product_packaging_type.pot
odoo/addons/product_packaging_type/models/__init__.py
odoo/addons/product_packaging_type/models/product_packaging_type.py
odoo/addons/product_packaging_type/readme/CONTRIBUTORS.rst
odoo/addons/product_packaging_type/readme/DESCRIPTION.rst
odoo/addons/product_packaging_type/readme/USAGE.rst
odoo/addons/product_packaging_type/security/ir.model.access.csv
odoo/addons/product_packaging_type/static/description/icon.png
odoo/addons/product_packaging_type/static/description/index.html
odoo/addons/product_packaging_type/views/product_packaging_type_view.xml
odoo/addons/product_packaging_type/views/product_packaging_view.xml
odoo12_addon_product_packaging_type-12.0.1.0.0.99.dev9.dist-info/METADATA
odoo12_addon_product_packaging_type-12.0.1.0.0.99.dev9.dist-info/WHEEL
odoo12_addon_product_packaging_type-12.0.1.0.0.99.dev9.dist-info/top_level.txt
odoo12_addon_product_packaging_type-12.0.1.0.0.99.dev9.dist-info/RECORD
